<?xml version="1.0" encoding="UTF-8"?>
<contents version="4.3.3" page="0" title="">
  <content page="1" title="Михаил Александрович Бакунин Протест &quot;Альянса&quot;"/>
  <content page="2" title="Краткая биография автора"/>
  <content page="3" title="Портрет автора"/>
  <content page="4" title="Протест &quot;Альянса&quot;">
    <content page="5" title="* * *"/>
    <content page="7" title="* * *"/>
    <content page="9" title="* * *"/>
    <content page="13" title="* * *"/>
  </content>
  <content page="31" title="Тех. характеристики издания"/>
  <content page="32" title="Конец"/>
</contents>
